pipen_cli_config/__init__.py
pipen_cli_config/defaults.py
pipen_cli_config/entry.py
pipen_cli_config/frontend/assets/favicon.png
pipen_cli_config/frontend/assets/global.css
pipen_cli_config/frontend/assets/markdown.css
pipen_cli_config/frontend/assets/normalize.css
pipen_cli_config/frontend/build/index.css
pipen_cli_config/frontend/build/index.js
pipen_cli_config/frontend/index.html
pipen_cli_config/frontend/schema/pipeline.json
pipen_cli_config/frontend/schema/schema.json
pipen_cli_config/misc.py
pipen_cli_config/utils.py
pipen_cli_config/version.py
pipen_cli_config-0.6.1.dist-info/METADATA
pipen_cli_config-0.6.1.dist-info/WHEEL
pipen_cli_config-0.6.1.dist-info/entry_points.txt
pipen_cli_config-0.6.1.dist-info/RECORD
