Metadata-Version: 2.1
Name: pipen-cli-config
Version: 0.6.1
Summary: UI wizard to generate configuration for pipen pipelines
License: MIT
Author: pwwang
Author-email: pwwang@pwwang.com
Requires-Python: >=3.7.1,<4.0.0
Classifier: License :: OSI Approved :: MIT License
Classifier: Programming Language :: Python :: 3
Classifier: Programming Language :: Python :: 3.8
Classifier: Programming Language :: Python :: 3.9
Classifier: Programming Language :: Python :: 3.10
Classifier: Programming Language :: Python :: 3.11
Requires-Dist: pipen (>=0.7,<0.8)
Requires-Dist: pipen-annotate (>=0.6,<0.7)
